suger/__init__.py
suger/common/FileCompareUtils.py
suger/common/FileUtils.py
suger/common/ObjectUtils.py
suger/common/StringUtils.py
suger/common/__init__.py
suger/data_operator/CsvUtils.py
suger/data_operator/ExcelUtils.py
suger/data_operator/JsonUtils.py
suger/data_operator/XmlUtils.py
suger/data_operator/__init__.py
suger/decorator/__init__.py
suger/decorator/csv_decorator.py
suger/decorator/string_decorator.py
suger/stream/Stream.py
suger/stream/__init__.py
suger/terminal/SSH.py
suger/terminal/TerminalUtils.py
suger/terminal/__init__.py
suger-0.2.2.dist-info/METADATA
suger-0.2.2.dist-info/WHEEL
suger-0.2.2.dist-info/licenses/LICENSE
suger-0.2.2.dist-info/RECORD
