Metadata-Version: 2.1
Name: suger
Version: 0.2.2
Summary: suger is a sugar. use python in @decorator/@Annotation like other languages~
Project-URL: Homepage, https://github.com/SolarisNeko/python-suger
Project-URL: Bug Tracker, https://github.com/SolarisNeko/python-suger/issues
Author-email: SolarisNeko <1417015340@qq.com>
License-File: LICENSE
Classifier: License :: OSI Approved :: MIT License
Classifier: Operating System :: OS Independent
Classifier: Programming Language :: Python :: 3
Requires-Python: >=3.7
